{
  "generatedAt": "2026-04-24T15:49:51.645196+00:00",
  "epigraph": {
    "quote": "恐怖と欲望、この二つの感情が金融市場を支配している。だが、最も危険なのは両者が同時に存在する時だ。",
    "source": "ハワード・マークス『投資で一番大切な20の教え』",
    "connection": "イラン情勢という恐怖と、史上最高値という欲望が同居する今日の市場を映し出す"
  },
  "headline_of_the_day": "日経平均が史上最高値更新、DOJ撤退でFed人事に道筋",
  "news": [
    {
      "tag": "金融政策",
      "headline": "米司法省がパウエル議長への捜査を取り下げ、ウォーシュ次期議長指名に道筋",
      "body": "トランプ政権の司法省がFRB議長パウエル氏に対する調査を取り下げた。5月15日の任期満了に向け、ケビン・ウォーシュ氏の議長就任承認プロセスが前進する見通し。市場は政策継続性への懸念が後退し、株式市場は上昇で反応。",
      "impact": [
        "短期:FRBリーダーシップの不確実性低下で米株にプラス",
        "中期:ウォーシュ氏の政策スタンス次第で金利見通しに変化"
      ],
      "source_index": 20,
      "link": "https://www.marketwatch.com/story/pirro-drops-probe-into-feds-powell-paving-way-for-warsh-confirmation-b77bc126?mod=mw_rss_topstories",
      "source": "MarketWatch Top"
    },
    {
      "tag": "日本株",
      "headline": "日経平均が史上最高値を更新、終値で6万円台乗せ視野",
      "body": "日経平均株価が反発し、終値ベースで史上最高値を更新した。ただし物色には偏りがあり、一部の大型株主導の上昇。原油高環境下でも円安と企業業績期待が株価を押し上げている。",
      "impact": [
        "短期:海外勢の買い継続がカギ",
        "中期:物色の裾野拡大なければ持続性に疑問"
      ],
      "source_index": 9,
      "link": "https://jp.reuters.com/markets/japan/6CTRATLWLZKWFMJBOSJ7ED5ZDI-2026-04-24/",
      "source": "Reuters Japan Markets"
    },
    {
      "tag": "地政学",
      "headline": "イラン情勢で独IFO業況指数が2020年以来の低水準に沈む",
      "body": "4月のドイツIFO業況指数がコロナ禍以来の低水準を記録。イラン情勢の緊迫化による先行き不透明感が企業心理を急速に悪化させている。欧州経済の牽引役であるドイツの失速は域内全体への波及リスク。",
      "impact": [
        "短期:欧州株・ユーロに下押し圧力",
        "中期:ECBの利下げ期待再燃の可能性"
      ],
      "source_index": 16,
      "link": "https://jp.reuters.com/markets/japan/5DSKMLBFARNVLIQWURMYOGPDHE-2026-04-24/",
      "source": "Reuters Japan Markets"
    },
    {
      "tag": "半導体",
      "headline": "Intel株が急騰、サーバーCPU好調と製造改善で過去最高値圏",
      "body": "Intel決算がサーバー向けCPUの強さと製造部門の改善を示し、株価が記録的な急騰。4つの転換イベントが同社のターンアラウンドを後押ししているとアナリストは分析。SOX指数も連れ高。",
      "impact": [
        "短期:半導体セクター全体にセンチメント改善",
        "中期:AMDやNVIDIAとの競争激化に注目"
      ],
      "source_index": 47,
      "link": "https://finance.yahoo.com/markets/stocks/article/intel-stock-surges-to-record-highs-these-4-events-have-powered-the-companys-turnaround-152804240.html",
      "source": "Yahoo Finance US"
    },
    {
      "tag": "エネルギー",
      "headline": "ホルムズ海峡正常化は7月以降か、予測市場で悲観見通し",
      "body": "Kalshiの予測市場で、ホルムズ海峡の交通正常化確率が50%を下回った。米イラン停戦延長にもかかわらず、市場参加者は7月まで混乱継続を織り込む。原油価格の高止まり要因として警戒。",
      "impact": [
        "短期:原油・天然ガス価格の上方圧力継続",
        "中期:世界経済のスタグフレーション懸念"
      ],
      "source_index": 35,
      "link": "https://www.cnbc.com/2026/04/23/kalshi-bettors-see-strait-of-hormuz-traffic-normal-by-july.html",
      "source": "CNBC Markets"
    },
    {
      "tag": "中国市場",
      "headline": "中国、外国人投資家に国債先物取引を解禁",
      "body": "中国当局が適格外国機関投資家に対し国債先物取引を解禁。リスク管理手段の拡充により、海外資金の中国債券市場への流入促進を狙う。資本市場開放の一環として注目される。",
      "impact": [
        "短期:中国国債への外国人投資フロー増加期待",
        "中期:人民元国際化の進展度合いに影響"
      ],
      "source_index": 15,
      "link": "https://jp.reuters.com/markets/japan/IXL2HCDL5NOMJK4ETX523NHPUU-2026-04-24/",
      "source": "Reuters Japan Markets"
    },
    {
      "tag": "クラウド・AI",
      "headline": "AmazonのGravitonチップにMeta大口採用、AI競争で存在感",
      "body": "AmazonがMetaからエージェントAI向けに数千万個規模のGravitonチップ採用を獲得。自社開発半導体がNVIDIA依存軽減の選択肢として評価され、Amazon株は過去最高値に接近。",
      "impact": [
        "短期:Amazon株・クラウドセクターに追い風",
        "中期:半導体サプライチェーンの多様化進展"
      ],
      "source_index": 26,
      "link": "https://www.marketwatch.com/story/amazons-chip-business-scores-another-major-win-6b65f2db?mod=mw_rss_topstories",
      "source": "MarketWatch Top"
    }
  ],
  "funny_stories": [
    {
      "kind": "皮肉",
      "title": "パウエル捜査の顛末",
      "body": "「FRB議長を追い詰めろ」と息巻いていた司法省が、結局は静かに矛を収めた。市場は「政治と金融政策の緊張」というドラマを期待していたが、最終回はあっけない和解エンド。次期議長ウォーシュ氏も「まあ、後任が決まってよかったね」という顔をしているに違いない。",
      "source_index": 20,
      "link": "https://www.marketwatch.com/story/pirro-drops-probe-into-feds-powell-paving-way-for-warsh-confirmation-b77bc126?mod=mw_rss_topstories",
      "source": "MarketWatch Top"
    },
    {
      "kind": "哀愁",
      "title": "マツダ2、静かに幕を閉じる",
      "body": "名車と呼ばれたマツダ2の国内生産が8月で終了する。かつて「デミオ」として愛されたあの車。「走る歓び」を小さなボディに詰め込み、初めてのマイカーとして多くの人の青春を乗せた。工場のラインが止まる日、誰かがそっとハンドルを握り締めるのだろう。",
      "source_index": 1,
      "link": "https://news.yahoo.co.jp/pickup/6577511?source=rss",
      "source": "Yahoo!ファイナンス"
    },
    {
      "kind": "観察",
      "title": "うな丼は下がり、親子丼は上がる",
      "body": "物価高の波が親子丼を直撃する一方、うな丼は値下げ。卵高騰と鰻の豊漁という需給のいたずらが、丼ものの価格序列を逆転させた。牛丼チェーンのメニュー表が、実は最もリアルタイムな物価指標かもしれない。",
      "source_index": 5,
      "link": "https://news.yahoo.co.jp/pickup/6577493?source=rss",
      "source": "Yahoo!ファイナンス"
    }
  ],
  "charts_of_the_day": [
    {
      "source": "yf",
      "ticker": "INTC",
      "title": "Intel",
      "name": "Intel",
      "sub": "",
      "rationale": "決算急騰で過去最高値圏、半導体ターンアラウンドの象徴として本日の主役"
    },
    {
      "source": "yf",
      "ticker": "^N225",
      "title": "日経平均",
      "name": "日経平均",
      "sub": "INDEX · JPY",
      "rationale": "史上最高値更新、原油高でも上昇継続する日本株の強さを確認"
    },
    {
      "source": "yf",
      "ticker": "CL=F",
      "title": "WTI原油",
      "name": "WTI原油",
      "sub": "$ / bbl",
      "rationale": "ホルムズ海峡リスクで高止まり、地政学プレミアムの行方"
    },
    {
      "source": "yf",
      "ticker": "^SOX",
      "title": "SOX半導体指数",
      "name": "SOX (半導体)",
      "sub": "INDEX · USD",
      "rationale": "Intel急騰がセクター全体に波及、半導体サイクル転換の兆候"
    },
    {
      "source": "yf",
      "ticker": "^GDAXI",
      "title": "ドイツDAX",
      "name": "ドイツDAX",
      "sub": "",
      "rationale": "IFO急落でも株価の反応を確認、欧州景気懸念の織り込み度合い"
    },
    {
      "source": "yf",
      "ticker": "JPY=X",
      "title": "ドル円",
      "name": "USD/JPY",
      "sub": "ドル円",
      "rationale": "Fed人事進展と日本株最高値、円安トレンド継続か要確認"
    },
    {
      "source": "yf",
      "ticker": "^VIX",
      "title": "VIX",
      "name": "VIX (恐怖指数)",
      "sub": "INDEX",
      "rationale": "株高とイラン情勢の綱引き、恐怖指数の位置を確認"
    },
    {
      "source": "yf",
      "ticker": "AMZN",
      "title": "Amazon",
      "name": "Amazon",
      "sub": "",
      "rationale": "Gravitonチップ大型受注で過去最高値接近、AI競争での立ち位置"
    }
  ],
  "deep_dive": {
    "title": "DOJのパウエル捜査撤回が意味するもの—Fed人事の行方と金融政策の転換点",
    "lede": "トランプ政権の司法省がFRB議長への調査を取り下げたことで、5月15日に予定されるウォーシュ新議長就任への道が開けた。これは単なる人事の話ではなく、米国金融政策の方向性を左右する歴史的転換点となりうる。",
    "background": "トランプ大統領は就任以来、パウエル議長の金融政策運営を「インフレを助長した」と批判し続けてきた。司法省による異例の調査開始は、中央銀行の独立性に対する挑戦と市場で受け止められ、一時は米国債とドルへの信認低下懸念まで浮上した。今回の調査撤回は、次期議長候補ケビン・ウォーシュ氏の承認プロセスを円滑に進めるための「手打ち」との見方が強い。ウォーシュ氏は2006-2011年にFRB理事を務め、金融危機対応に携わった経験を持つ。",
    "implications": "短期的にはFedリーダーシップの不確実性解消で株式市場にプラス。だが中期的な焦点はウォーシュ氏の政策スタンスだ。同氏はパウエル氏より「タカ派寄り」との評価がある一方、トランプ政権との距離感も注目される。FRBの独立性がどこまで維持されるかは、米国債の信認、ドルの基軸通貨としての地位に直結する。市場は当面、5月15日の就任と最初のFOMC声明を固唾を呑んで見守ることになる。長期的には、インフレ目標や金融緩和の出口戦略に関する路線変更の有無がカギを握る。",
    "what_to_watch": [
      "5月15日のウォーシュ議長就任と初の公式発言",
      "6月FOMCでの政策声明と金利見通し(ドットプロット)",
      "トランプ大統領とウォーシュ氏の公の関係性",
      "米国債利回りと長短金利差の動向",
      "ドル指数(DXY)の反応—Fed独立性への信認バロメーター"
    ],
    "related_keys": [
      "us10y",
      "dxy",
      "sp500",
      "vix"
    ],
    "source_index": 20,
    "link": "https://www.marketwatch.com/story/pirro-drops-probe-into-feds-powell-paving-way-for-warsh-confirmation-b77bc126?mod=mw_rss_topstories",
    "source": "MarketWatch Top"
  }
}